wpiutil/__init__.py
wpiutil/_stacktrace.py
wpiutil/py.typed
wpiutil/version.py
wpiutil/log/__init__.py
wpiutil/src/main.cpp
wpiutil/src/safethread_gil.cpp
wpiutil/src/stacktracehook.cpp
wpiutil/src/type_casters/wpi_array_type_caster.h
wpiutil/src/type_casters/wpi_ct_string_type_caster.h
wpiutil/src/type_casters/wpi_json_type_caster.h
wpiutil/src/type_casters/wpi_smallset_type_caster.h
wpiutil/src/type_casters/wpi_smallvector_type_caster.h
wpiutil/src/type_casters/wpi_smallvectorimpl_type_caster.h
wpiutil/src/type_casters/wpi_span_type_caster.h
wpiutil/src/type_casters/wpi_string_map_caster.h
wpiutil/src/wpistruct/wpystruct.h
wpiutil/src/wpistruct/wpystruct_fns.cpp
wpiutil/src/wpistruct/wpystruct_fns.h
wpiutil/sync/__init__.py
wpiutil/wpistruct/__init__.py
wpiutil/wpistruct/dataclass.py
wpiutil/wpistruct/desc.py
wpiutil/wpistruct/typing.py
wpiutil/_init__wpiutil.py
wpiutil/_wpiutil.cpython-39-darwin.so
wpiutil/wpiutil-casters.pc
wpiutil/wpiutil-casters.pybind11.json
wpiutil/wpiutil.pc
wpiutil/_wpiutil/__init__.pyi
wpiutil/_wpiutil/log.pyi
wpiutil/_wpiutil/sync.pyi
wpiutil/_wpiutil/wpistruct.pyi
wpiutil/trampolines/wpi__Sendable.hpp
wpiutil/trampolines/wpi__SendableBuilder.hpp
wpiutil/trampolines/wpi__SendableRegistry.hpp
wpiutil/trampolines/wpi__log__BooleanArrayLogEntry.hpp
wpiutil/trampolines/wpi__log__BooleanLogEntry.hpp
wpiutil/trampolines/wpi__log__DataLog.hpp
wpiutil/trampolines/wpi__log__DataLogBackgroundWriter.hpp
wpiutil/trampolines/wpi__log__DataLogEntry.hpp
wpiutil/trampolines/wpi__log__DataLogReader.hpp
wpiutil/trampolines/wpi__log__DataLogRecord.hpp
wpiutil/trampolines/wpi__log__DataLogValueEntryImpl.hpp
wpiutil/trampolines/wpi__log__DataLogWriter.hpp
wpiutil/trampolines/wpi__log__DoubleArrayLogEntry.hpp
wpiutil/trampolines/wpi__log__DoubleLogEntry.hpp
wpiutil/trampolines/wpi__log__FloatArrayLogEntry.hpp
wpiutil/trampolines/wpi__log__FloatLogEntry.hpp
wpiutil/trampolines/wpi__log__IntegerArrayLogEntry.hpp
robotpy_wpiutil-2025.3.2.3.dist-info/METADATA
robotpy_wpiutil-2025.3.2.3.dist-info/WHEEL
robotpy_wpiutil-2025.3.2.3.dist-info/entry_points.txt
robotpy_wpiutil-2025.3.2.3.dist-info/RECORD
