Metadata-Version: 2.4
Name: robotpy-wpiutil
Version: 2025.3.2.3
Summary: Binary wrapper for FRC WPIUtil library
Project-URL: Source code, https://github.com/robotpy/mostrobotpy
Author-email: RobotPy Development Team <robotpy@googlegroups.com>
License-Expression: BSD-3-Clause
Requires-Dist: robotpy-native-wpiutil==2025.3.2
